sb3/__init__.py
sb3/block.py
sb3/excs.py
sb3/gclass.py
sb3/monitor.py
sb3/project_json.py
sb3/sprite.py
sb3/unzipper.py
testing/__init__.py
sb3-0.1.dist-info/LICENSE
sb3-0.1.dist-info/METADATA
sb3-0.1.dist-info/WHEEL
sb3-0.1.dist-info/top_level.txt
sb3-0.1.dist-info/RECORD
